[{"__type__":"cc.SpriteFrame","content":{"name":"hit_L_m_8","texture":"43lTVF3p5LvK6Z+OycrYq8","rect":[237,5,155,247],"offset":[21,-2.5],"originalSize":[587,252],"capInsets":[0,0,0,0]}},{"__type__":"cc.SpriteFrame","content":{"name":"hit_L_m_7","texture":"90hYT8GmVDgbVAtdnf0gjv","rect":[237,5,155,247],"offset":[21,-2.5],"originalSize":[587,252],"capInsets":[0,0,0,0]}},{"__type__":"cc.AnimationClip","_name":"hit_l_m","_duration":0.25,"curveData":{"comps":{"cc.Sprite":{"spriteFrame":[{"frame":0,"value":{"__uuid__":"bbx+O1jElPKJsviF0UBely"}},{"frame":0.03333333333333333,"value":{"__uuid__":"cf2SuuhOZEs7Z2TrmO5jqE"}},{"frame":0.06666666666666667,"value":{"__uuid__":"d9ihjR6CJP6JbrYAL7Teex"}},{"frame":0.1,"value":{"__uuid__":"520RuFucdHno9Vg3Otpruh"}},{"frame":0.13333333333333333,"value":{"__uuid__":"c6rJZQqhxDCpjLBLfkiSx2"}},{"frame":0.16666666666666666,"value":{"__uuid__":"9fS1CUfwVHnJUXz/EP1B/G"}},{"frame":0.2,"value":{"__uuid__":"06ilxCdn9CN71wUWY3+t+j"}},{"frame":0.23333333333333334,"value":{"__uuid__":"00kYKmSXZJ9rDSPuie76mN"}}]}}}},{"__type__":"cc.SpriteFrame","content":{"name":"hit_L_m_4","texture":"958t2y09JMH6uJyGj1jjpu","rect":[237,5,155,247],"offset":[21,-2.5],"originalSize":[587,252],"capInsets":[0,0,0,0]}},{"__type__":"cc.SpriteFrame","content":{"name":"hit_L_m_6","texture":"63mZUWjhNAxoEfwvwbSyMI","rect":[237,5,155,247],"offset":[21,-2.5],"originalSize":[587,252],"capInsets":[0,0,0,0]}},{"__type__":"cc.SpriteFrame","content":{"name":"hit_L_m_1","texture":"1dcSlm6OFEDaz9j/+fJPIN","rect":[237,32,112,220],"offset":[-0.5,-16],"originalSize":[587,252],"capInsets":[0,0,0,0]}},{"__type__":"cc.SpriteFrame","content":{"name":"hit_L_m_5","texture":"ebHc6L8u5DArzAPN5rUpoy","rect":[237,5,155,247],"offset":[21,-2.5],"originalSize":[587,252],"capInsets":[0,0,0,0]}},{"__type__":"cc.SpriteFrame","content":{"name":"hit_L_m_2","texture":"46tlIMvQhIyp3sOGOI7OKB","rect":[219,46,130,206],"offset":[-9.5,-23],"originalSize":[587,252],"capInsets":[0,0,0,0]}},{"__type__":"cc.SpriteFrame","content":{"name":"hit_L_m_3","texture":"f5LCl7R7lNrIi/phutkZWK","rect":[237,5,155,247],"offset":[21,-2.5],"originalSize":[587,252],"capInsets":[0,0,0,0]}}]